gpapidl/__init__.py
gpapidl/config.py
gpapidl/device.properties
gpapidl/googleplay.py
gpapidl/googleplay_pb2.py
gpapidl/utils.py
bst_gpapidl-1.0.2.dist-info/LICENSE.md
bst_gpapidl-1.0.2.dist-info/METADATA
bst_gpapidl-1.0.2.dist-info/WHEEL
bst_gpapidl-1.0.2.dist-info/top_level.txt
bst_gpapidl-1.0.2.dist-info/RECORD
